winapps/__init__.py
winapps-0.1.6.dist-info/LICENSE
winapps-0.1.6.dist-info/WHEEL
winapps-0.1.6.dist-info/METADATA
winapps-0.1.6.dist-info/RECORD
