Metadata-Version: 2.1
Name: winapps
Version: 0.1.6
Summary: Python library for managing installed applications on Windows
Home-page: https://github.com/rominf/winapps
Author: Roman Inflianskas
Author-email: infroma@gmail.com
Keywords: library,windows,apps,applications,programs,management
Requires-Python: >=3.6,<4.0
Classifier: Development Status :: 3 - Alpha
Classifier: Environment :: Win32 (MS Windows)
Classifier: Intended Audience :: Developers
Classifier: Intended Audience :: System Administrators
Classifier: License :: OSI Approved :: Apache Software License
Classifier: Operating System :: Microsoft :: Windows
Classifier: Programming Language :: Python :: 3
Classifier: Programming Language :: Python :: 3.6
Classifier: Programming Language :: Python :: 3.7
Classifier: Topic :: Software Development :: Libraries :: Python Modules
Classifier: Topic :: System :: Software Distribution
Classifier: Topic :: System :: Systems Administration
Requires-Dist: dataclasses (>=0.6.0,<0.7.0); python_version >= "3.6" and python_version < "3.7"
Requires-Dist: plumbum (>=1.6,<2.0)
Project-URL: Repository, https://github.com/rominf/winapps
